[{"name":"sql.active_record","payload":{"sql":"SELECT  \"users\".* FROM \"users\" WHERE \"users\".\"id\" = $1 LIMIT 1","name":"User Load","connection_id":70306819546620,"statement_name":"a2","binds":[[{"array":false,"name":"id","cast_type":{"precision":null,"scale":null,"limit":null,"range":"-2147483648...2147483648"},"sql_type":"integer","null":false,"default":null,"default_function":"nextval('users_id_seq'::regclass)"},73]],"line":11,"filename":"/Users/xander/Desktop/project1/app/controllers/application_controller.rb","method":"authenticate"},"time":"2015-02-12T21:38:40.822+11:00","transaction_id":"0ab0b06aeb502bde39c8","end":"2015-02-12T21:38:40.822+11:00","children":[],"duration":0.5720000000000001},{"name":"sql.active_record","payload":{"sql":"SELECT  1 AS one FROM \"meals\" WHERE \"meals\".\"user_id\" = $1 LIMIT 1","name":"Meal Exists","connection_id":70306819546620,"statement_name":"a11","binds":[[{"array":false,"name":"user_id","cast_type":{"precision":null,"scale":null,"limit":null,"range":"-2147483648...2147483648"},"sql_type":"integer","null":true,"default":null,"default_function":null},73]],"line":5,"filename":"/Users/xander/Desktop/project1/app/views/meals/index.html.erb","method":"_app_views_meals_index_html_erb__3028646228478861623_70306834176240"},"time":"2015-02-12T21:38:40.854+11:00","transaction_id":"0ab0b06aeb502bde39c8","end":"2015-02-12T21:38:40.854+11:00","children":[],"duration":0.5339999999999999},{"name":"sql.active_record","payload":{"sql":"SELECT \"meals\".* FROM \"meals\" WHERE \"meals\".\"user_id\" = $1","name":"Meal Load","connection_id":70306819546620,"statement_name":"a3","binds":[[{"array":false,"name":"user_id","cast_type":{"precision":null,"scale":null,"limit":null,"range":"-2147483648...2147483648"},"sql_type":"integer","null":true,"default":null,"default_function":null},73]],"line":10,"filename":"/Users/xander/Desktop/project1/app/views/meals/index.html.erb","method":"_app_views_meals_index_html_erb__3028646228478861623_70306834176240"},"time":"2015-02-12T21:38:40.856+11:00","transaction_id":"0ab0b06aeb502bde39c8","end":"2015-02-12T21:38:40.857+11:00","children":[],"duration":0.717},{"name":"render_template.action_view","payload":{"identifier":"/Users/xander/Desktop/project1/app/views/meals/index.html.erb","layout":"layouts/application"},"time":"2015-02-12T21:38:40.853+11:00","transaction_id":"fa5845fb2e7a0639b6a1","end":"2015-02-12T21:38:40.859+11:00","children":[],"duration":6.436},{"name":"process_action.action_controller","payload":{"controller":"MealsController","action":"index","params":{"controller":"meals","action":"index","format":"73"},"format":null,"method":"GET","path":"/meals.73","status":200,"view_runtime":137.7433199410066,"db_runtime":0.847},"time":"2015-02-12T21:38:40.821+11:00","transaction_id":"fa5845fb2e7a0639b6a1","end":"2015-02-12T21:38:40.963+11:00","children":[],"duration":141.225}]